[
  {
    "id": 1,
    "view": true,
    "icon": "bx bx-user",
    "active": false,
    "name": "Usuarios",
    "path": "/usuarios/consulta",
    "roles": [
      {
        "name": "Administrador"
      }
    ],
    "submenu": []
  },
  {
    "id": 2,
    "icon": "bx bx-group",
    "view": true,
    "active": false,
    "name": "Proveedores",
    "path": "/proveedores",
    "roles": [
      {
        "name": "Administrador"
      },
      {
        "name": "Secretaria"
      }
    ],
    "submenu": [
      {
        "view": true,
        "name": "consulta",
        "path": "/proveedores/consulta",
        "roles": [
          {
            "name": "Administrador"
          },
          {
            "name": "Secretaria"
          }
        ]
      },
      {
        "view": true,
        "name": "crear",
        "path": "/proveedores/creacion",
        "roles": [
          {
            "name": "Administrador"
          }
        ]
      }
    ]
  },
  {
    "id": 3,
    "icon": "bx bx-cart",
    "view": true,
    "active": false,
    "name": "Adquisicion",
    "path": "/adquisiciones",
    "roles": [
      {
        "name": "Administrador"
      },
      {
        "name": "Secretaria"
      }
    ],
    "submenu": [
      {
        "view": true,
        "name": "consulta",
        "path": "/adquisiciones/consulta",
        "roles": [
          {
            "name": "Administrador"
          },
          {
            "name": "Secretaria"
          }
        ]
      },
      {
        "view": true,
        "name": "crear",
        "path": "/adquisiciones/creacion",
        "roles": [
          {
            "name": "Administrador"
          }
        ]
      }
    ]
  },
  {
    "id": 4,
    "icon": "bx bx-money",
    "view": true,
    "active": false,
    "name": "Cotizaciones",
    "path": "/cotizaciones",
    "roles": [
      {
        "name": "Administrador"
      },
      {
        "name": "Secretaria"
      }
    ],
    "submenu": [
      {
        "view": true,
        "name": "consulta",
        "path": "/cotizaciones/consulta",
        "roles": [
          {
            "name": "Administrador"
          },
          {
            "name": "Secretaria"
          }
        ]
      },
      {
        "view": true,
        "name": "crear",
        "path": "/cotizaciones/creacion",
        "roles": [
          {
            "name": "Administrador"
          }
        ]
      }
    ]
  }
]
